bin/concrt140.dll
bin/msvcp140.dll
bin/msvcp140_1.dll
bin/msvcp140_2.dll
bin/msvcp140_atomic_wait.dll
bin/msvcp140_codecvt_ids.dll
bin/vcruntime140.dll
bin/vcruntime140_1.dll
include/RVO/Export.h
include/RVO/Line.h
include/RVO/RVO.h
include/RVO/RVOSimulator.h
include/RVO/Vector2.h
lib/cmake/RVO/RVOConfig.cmake
lib/cmake/RVO/RVOConfigVersion.cmake
lib/cmake/RVO/RVOTargets-release.cmake
lib/cmake/RVO/RVOTargets.cmake
lib/RVO.lib
pyrvo/__init__.py
pyrvo/CMakeLists.txt
pyrvo/orca_bind.cpp
pyrvo/pyrvo.pypy39-pp73-win_amd64.pyd
pyrvo/src/Agent.cc
pyrvo/src/Agent.h
pyrvo/src/CMakeLists.txt
pyrvo/src/Export.cc
pyrvo/src/KdTree.cc
pyrvo/src/KdTree.h
pyrvo/src/Line.cc
pyrvo/src/Line.h
pyrvo/src/Obstacle.cc
pyrvo/src/Obstacle.h
pyrvo/src/RVO.h
pyrvo/src/RVOSimulator.cc
pyrvo/src/RVOSimulator.h
pyrvo/src/Vector2.cc
pyrvo/src/Vector2.h
share/doc/RVO/LICENSE
pyrvo-0.4.3.dist-info/METADATA
pyrvo-0.4.3.dist-info/WHEEL
pyrvo-0.4.3.dist-info/RECORD
