Metadata-Version: 2.2
Name: pyrvo
Version: 0.4.3
Summary: Python bindings for ORCA (Optimal Reciprocal Collision Avoidance) library
Author-Email: Han Ruihua <hanrh@connect.hku.hk>
Classifier: Development Status :: 3 - Alpha
Classifier: Intended Audience :: Science/Research
Classifier: Programming Language :: Python :: 3.9
Classifier: Programming Language :: Python :: 3.10
Classifier: Programming Language :: Python :: 3.11
Classifier: Programming Language :: Python :: 3.12
Classifier: Programming Language :: Python :: 3.13
Classifier: Topic :: Scientific/Engineering :: Physics
Project-URL: Repository, https://github.com/hanruihua/pyrvo
Project-URL: Homepage, https://github.com/hanruihua/pyrvo
Requires-Python: >=3.9
Requires-Dist: ir-sim
